{
  "skillsite": [
    {
      "companyTitle": "JUA KALI STATES",
      "skill": "Metall Carving",
      "about": "our company is geared to help fresh graduates to acquire fresh skills that may aid them in setting up their own businesses.Student learn the metall art craft in building home furnitures and industrial items. We are located at mpanda juu floor in nairobi. Contact us on 07493342344 ",
      "id": 2
    },
    {
      "companyTitle": "Wajackoya Bakery system",
      "skill": "Baking",
      "about": "our company is geared to help fresh graduates to acquire fresh skills that may aid them in setting up their own businesses.Student learn the baking artistry. We are located at Malia floor in nairobi. Contact us on 07493342344 ",
      "id": 4
    },
    {
      "companyTitle": "RUTO FARMING INDUSTRY ",
      "skill": "farming",
      "about": "edfsf pgpfdogkvfb ;k;fgb f;dfbm vjfgo fogudfpdsp ",
      "id": 5
    }
  ]
}